playlist_summarizer_cli/__init__.py
playlist_summarizer_cli/__main__.py
playlist_summarizer_cli/main.py
playlist_summarizer_cli-0.1.0.dist-info/WHEEL
playlist_summarizer_cli-0.1.0.dist-info/entry_points.txt
playlist_summarizer_cli-0.1.0.dist-info/METADATA
playlist_summarizer_cli-0.1.0.dist-info/RECORD
