Metadata-Version: 2.3
Name: playlist-summarizer-cli
Version: 0.1.0
Summary: CLI tool for fetching YouTube playlist transcripts and generating AI-powered summaries
Keywords: youtube,playlist,transcript,summarizer,ai,ollama,llm,cli
Author: Anthony Kovach
Author-email: Anthony Kovach <aj@ajxd2.dev>
Classifier: Development Status :: 4 - Beta
Classifier: Intended Audience :: Developers
Classifier: License :: OSI Approved :: MIT License
Classifier: Programming Language :: Python :: 3
Classifier: Programming Language :: Python :: 3.14
Classifier: Topic :: Multimedia :: Video
Classifier: Topic :: Text Processing :: Markup
Classifier: Topic :: Utilities
Requires-Dist: playlist-summarizer-core
Requires-Dist: inquirer>=3.4.1
Requires-Dist: python-dotenv>=1.2.1
Requires-Dist: rich>=14.2.0
Requires-Python: >=3.14
